wheelify/__init__.py
wheelify/app.py
wheelify-0.1.4.dist-info/DESCRIPTION.rst
wheelify-0.1.4.dist-info/METADATA
wheelify-0.1.4.dist-info/RECORD
wheelify-0.1.4.dist-info/WHEEL
wheelify-0.1.4.dist-info/entry_points.txt
wheelify-0.1.4.dist-info/metadata.json
wheelify-0.1.4.dist-info/top_level.txt
