Metadata-Version: 2.0
Name: wheelify
Version: 0.1.4
Summary: Simple manylinux wheel builder utility
Home-page: https://github.com/jmvrbanac/wheelify
Author: John Vrbanac
Author-email: john.vrbanac@linux.com
License: Apache v2
Keywords: manylinux wheel builder
Platform: UNKNOWN
Classifier: Development Status :: 3 - Alpha
Classifier: Intended Audience :: Developers
Classifier: License :: OSI Approved :: Apache Software License
Classifier: Programming Language :: Python :: 3.6
